<Properties StartupConfiguration="{747AF7C0-35C8-46B6-9674-9583F1242B75}|Default">
  <MonoDevelop.Ide.Workbench ActiveDocument="SoloDevApp.Service/Services/BinhLuanService.cs">
    <Files>
      <File FileName="SoloDevApp.Api/Controllers/BinhLuanController.cs" Line="73" Column="50" />
      <File FileName="SoloDevApp.Service/Services/BinhLuanService.cs" Line="21" Column="1" />
      <File FileName="SoloDevApp.Service/ViewModels/GetBinhLuanView.cs" Line="9" Column="28" />
    </Files>
    <Pads>
      <Pad Id="ProjectPad">
        <State name="__root__">
          <Node name="SoloDevApp" expanded="True">
            <Node name="SoloDevApp.Api" expanded="True">
              <Node name="Controllers" expanded="True" />
            </Node>
            <Node name="SoloDevApp.Repository" expanded="True">
              <Node name="Infrastructure" expanded="True" />
              <Node name="Models" expanded="True" />
            </Node>
            <Node name="SoloDevApp.Service" expanded="True">
              <Node name="Helpers" expanded="True" />
              <Node name="Services" expanded="True" />
              <Node name="ViewModels" expanded="True" />
            </Node>
          </Node>
        </State>
      </Pad>
      <Pad Id="MonoDevelop.Debugger.WatchPad">
        <State />
      </Pad>
    </Pads>
  </MonoDevelop.Ide.Workbench>
  <MonoDevelop.Ide.DebuggingService.PinnedWatches />
  <MonoDevelop.Ide.Workspace ActiveConfiguration="Debug" />
  <MonoDevelop.Ide.DebuggingService.Breakpoints>
    <BreakpointStore />
  </MonoDevelop.Ide.DebuggingService.Breakpoints>
  <MonoDevelop.Ide.ItemProperties.SoloDevApp.Api PreferredExecutionTarget="/Applications/Google Chrome.app" />
  <MultiItemStartupConfigurations />
</Properties>